ui_tars/1.py
ui_tars/__init__.py
ui_tars/action_parser.py
ui_tars/formatter_xml02.py
ui_tars/formatter_xml02_sptoken.py
ui_tars/formatter_xml03.py
ui_tars/formatter_xml04.py
ui_tars/formatter_xml05.py
ui_tars/formatter_xml06.py
ui_tars/formatter_xml65.py
ui_tars/prompt.py
ui_tars-0.4.6.2.dist-info/METADATA
ui_tars-0.4.6.2.dist-info/WHEEL
ui_tars-0.4.6.2.dist-info/RECORD
