Metadata-Version: 2.4
Name: ui-tars
Version: 0.4.6.2
Summary: Parsing LLM-generated GUI action instructions, automatically generating pyautogui scripts, and supporting coordinate conversion and smart image resizing.
Author-email: "liangshihao.0828" <liangshihao.0828@bytedance.com>, jinxin001 <jinxin001@bytedance.com>
Requires-Python: <4.0,>=3.9
Requires-Dist: jsonschema
